ioc_parser_ng-0.9.2.data/scripts/iocp-ng
iocp/Output.py
iocp/Parser.py
iocp/__init__.py
iocp/data/patterns.ini
iocp/data/whitelists/whitelist_CVE.ini
iocp/data/whitelists/whitelist_Email.ini
iocp/data/whitelists/whitelist_Filename.ini
iocp/data/whitelists/whitelist_Filepath.ini
iocp/data/whitelists/whitelist_Host.ini
iocp/data/whitelists/whitelist_IP.ini
iocp/data/whitelists/whitelist_MD5.ini
iocp/data/whitelists/whitelist_Registry.ini
iocp/data/whitelists/whitelist_SHA1.ini
iocp/data/whitelists/whitelist_SHA256.ini
iocp/data/whitelists/whitelist_URL.ini
ioc_parser_ng-0.9.2.dist-info/LICENSE.txt
ioc_parser_ng-0.9.2.dist-info/METADATA
ioc_parser_ng-0.9.2.dist-info/WHEEL
ioc_parser_ng-0.9.2.dist-info/top_level.txt
ioc_parser_ng-0.9.2.dist-info/RECORD
