Metadata-Version: 2.1
Name: ioc-parser-ng
Version: 0.9.2
Summary: Tool to extract indicators of compromise from security reports, next generation
Home-page: https://gitlab.com/cincan/ioc_parser
Author: Kimmo Linnavuo
Author-email: kimmo.linnavuo@gmail.com
License: MIT
Platform: UNKNOWN
Classifier: Programming Language :: Python :: 3
Classifier: Development Status :: 4 - Beta
Classifier: Topic :: Security
Classifier: License :: OSI Approved :: MIT License
Requires-Python: >=3.5
Requires-Dist: beautifulsoup4 (>=4.8.2)
Requires-Dist: pdfminer.six (>=20200124)
Requires-Dist: PyPDF2 (>=1.26.0)
Requires-Dist: requests (>=2.22.0)
Requires-Dist: lxml (>=4.5.0)
Requires-Dist: docx2txt (>=0.8)
Requires-Dist: openpyxl (>=3.0.3)
Requires-Dist: ioc-fanger (>=3.0.18)
Requires-Dist: pdftotext (>=2.1.4)
Requires-Dist: pymispwarninglists (>=1.0)
